stelladb/__init__.py
stelladb/_version.py
stelladb/db_desc.py
stelladb/db_vmec.py
stelladb/device.py
stelladb/getters.py
stelladb-0.2.13.dist-info/LICENSE
stelladb-0.2.13.dist-info/METADATA
stelladb-0.2.13.dist-info/WHEEL
stelladb-0.2.13.dist-info/top_level.txt
stelladb-0.2.13.dist-info/RECORD
