Metadata-Version: 2.1
Name: stelladb
Version: 0.2.13
Summary: Includes functions to upload DESC and VMEC data to the stellarator database.
Home-page: https://github.com/PlasmaControl/Stellarator-Database/
Author: Yigit Gunsur Elmacioglu, Rory Conlin, Dario Panici, Egemen Kolemen
Author-email: PlasmaControl@princeton.edu
License: MIT
Keywords: stellarator tokamak equilibrium perturbation mhd magnetohydrodynamics stability confinement plasma physics optimization design fusion data database
Requires-Python: >=3.9
License-File: LICENSE
Requires-Dist: desc-opt
Requires-Dist: selenium
Requires-Dist: simsopt
